api_etl/__init__.py
api_etl/admin.py
api_etl/apps.py
api_etl/gql_mutations.py
api_etl/gql_queries.py
api_etl/models.py
api_etl/schema.py
api_etl/urls.py
api_etl/utils.py
api_etl/views.py
api_etl/adapters/__init__.py
api_etl/adapters/base.py
api_etl/adapters/exampleIndividialAdapter.py
api_etl/auth_provider/__init__.py
api_etl/auth_provider/base.py
api_etl/auth_provider/basicAuthProvider.py
api_etl/auth_provider/bearerAuthProvider.py
api_etl/auth_provider/noAuthAuthProvider.py
api_etl/migrations/__init__.py
api_etl/services/__init__.py
api_etl/services/base.py
api_etl/services/exampleIndividualETLService.py
api_etl/sinks/__init__.py
api_etl/sinks/base.py
api_etl/sinks/individual_import_sink.py
api_etl/sources/__init__.py
api_etl/sources/base.py
api_etl/sources/exampleIndividualSource.py
api_etl/tests/__init__.py
api_etl/tests/test_exampleIndividialAdapter.py
api_etl/tests/test_exampleIndividualETLService.py
api_etl/tests/test_individual_import_sink.py
api_etl/tests/test_utils.py
openimis_be_api_etl-1.2.0.dist-info/licenses/LICENSE.md
openimis_be_api_etl-1.2.0.dist-info/METADATA
openimis_be_api_etl-1.2.0.dist-info/WHEEL
openimis_be_api_etl-1.2.0.dist-info/top_level.txt
openimis_be_api_etl-1.2.0.dist-info/RECORD
